{"Return": {"ReturnHeader": {"PreparerFirm": {"PreparerFirmBusinessName": {"BusinessNameLine1": "GRAY ENTERPRISES"}, "PreparerFirmUSAddress": {"AddressLine1": "9363 DEVILBISS BRIDGE RD", "City": "WALKERSVILLE", "State": "MD", "ZIPCode": "21793"}}, "Filer": {"Name": {"BusinessNameLine1": "CLUSTERED SPIRES CEMETERY INC"}, "USAddress": {"AddressLine1": "9501 US RT 15 N", "City": "FREDERICK", "State": "MD", "ZIPCode": "21701"}, "EIN": "010810191", "NameControl": "CLUS"}, "Officer": {"Name": "RICHARD F CODY", "Title": "PRESIDENT", "Phone": "3016396591", "DateSigned": "2011-08-11", "AuthorizeThirdParty": "false"}, "Preparer": {"Name": "Sharon J Gray EA", "Phone": "3018987304", "DatePrepared": "2011-08-11"}, "Timestamp": "2011-08-11T15:28:33-04:00", "TaxPeriodEndDate": "2010-12-31", "ReturnType": "990EZ", "TaxPeriodBeginDate": "2010-01-01", "TaxYear": "2010", "BuildTS": "2016-02-24 21:20:13Z"}, "ReturnData": {"IRS990EZ": {"CashSavingsAndInvestments": {"BOY": "196852", "EOY": "182091"}, "LandAndBuildings": {"BOY": "58571", "EOY": "57984"}, "OtherAssetsTotal": {"BOY": "0", "EOY": "0"}, "TotalAssets": {"BOY": "255423", "EOY": "240075"}, "SumOfTotalLiabilities": {"BOY": "48112", "EOY": "50006"}, "NetAssetsOrFundBalances": {"BOY": "207311", "EOY": "190069"}, "ProgramServiceAccomplishment": {"DescriptionProgramServiceAccom": "RESTORATION OF HISTORUC GRAVE MARKERS GENERAL UPKEEP OF CEMETERY", "ProgramServiceExpenses": "29308"}, "OfficerDirectorTrusteeKeyEmpl": [{"AddressUS": {"AddressLine1": "9501 US RT 15 N", "City": "FREDERICK", "State": "MD", "ZIPCode": "21701"}, "PersonName": "RICHARD F CODY", "Title": "PRESIDENT DIRE", "AvgHoursPerWkDevotedToPosition": "0", "Compensation": "0", "ContriToEmplBenefitPlansEtc": "0", "ExpenseAccountOtherAllowances": "0"}, {"AddressUS": {"AddressLine1": "9501 US RT 15 N", "City": "FREDERICK", "State": "MD", "ZIPCode": "21701"}, "PersonName": "SKKOT CODY", "Title": "VICE PRESIDENT", "AvgHoursPerWkDevotedToPosition": "0", "Compensation": "0", "ContriToEmplBenefitPlansEtc": "0", "ExpenseAccountOtherAllowances": "0"}, {"AddressUS": {"AddressLine1": "9501 US RT 15 N", "City": "FREDERICK", "State": "MD", "ZIPCode": "21701"}, "PersonName": "JANET B CODY", "Title": "SECRETARYDIREC", "AvgHoursPerWkDevotedToPosition": "0", "Compensation": "0", "ContriToEmplBenefitPlansEtc": "0", "ExpenseAccountOtherAllowances": "0"}], "TheBooksAreInCareOf": {"AddressUS": {"AddressLine1": "9501 US RT 15 N", "City": "FREDERICK", "State": "MD", "ZIPCode": "21701"}, "NamePerson": "RICHARD F CODY", "TelephoneNumber": "3016396591"}, "MethodOfAccountingCash": "X", "ScheduleBNotRequired": "X", "Organization501c@typeOf501cOrganization": "13", "Organization501c": "X", "GrossReceipts": "70394", "InfoInScheduleOPartI": "X", "ContributionsGiftsGrantsEtc": "8076", "ProgramServiceRevenue": "24051", "InvestmentIncome": "2342", "GrossAmountFromSaleOfAssets": "35925", "CostOtherBasisAndSalesExpenses": "58330", "GainOrLossFromSaleOfAssets": "-22405", "TotalRevenue": "12064", "FeesAndOthPymtToIndContractors": "12724", "OccupancyRentUtilitiesAndMaint": "14105", "PrintingPublicationsPostage": "289", "OtherExpensesTotal": "2188", "TotalExpenses": "29306", "ExcessOrDeficitForYear": "-17242", "NetAssetsOrFundBalancesBOY": "207311", "NetAssetsOrFundBalancesEOY": "190069", "InfoInScheduleOPartII": "X", "PrimaryExemptPurpose": "CEMETERY FOR HUMAN DEAD", "TotalProgramServiceExpenses": "29308", "ActivitiesNotPreviouslyRpt": "false", "MadeChangesToOrgnzngEtcDoc": "false", "OrganizationHadUBI": "false", "OrganizationDissolvedEtc": "false", "DidOrgFileForm1120POLThisYear": "false", "MadeLoansToFromOfficers": "false", "ProhibitedTaxShelterTrans": "false", "StatesWhereCopyOfReturnIsFiled": "MD", "ForeignFinancialAccount": "false", "ForeignOffice": "false", "MaintainAnyDonorAdvisedFunds": "false", "DoesOrgHaveHospital": "false", "TanningServicesProvided": "false", "RelatedOrgControlledEntity": "false", "TransactionWithControlEntity": "false", "EngagePoliticalCmpgnActivities": "false", "FiledScheduleA": "false"}, "IRS990ScheduleO": {"GeneralExplanation": [{"Identifier": "01. Description of other expenses (Part I, line 16)", "Explanation": "DESCRIPTION AMOUNT INSURANCE 275 INTEREST 1316 MISC 497 CONFERENCE 100"}, {"Identifier": "02. Description of total liabilities (Part II, line 26)", "Explanation": "BEGINNING CATEGORY OF YEAR END OF YEAR LOAN 556 0 KUBOTA CREDIT 29500 23500 RESTHAVEN 18056 14506 KUBOTA 29269966 0 12000"}]}, "IRS990EZ@documentId": "990EZ", "IRS990ScheduleC@documentId": "990C", "IRS990ScheduleO@documentId": "990O"}, "ReturnHeader@binaryAttachmentCount": "0", "ReturnData@documentCount": "3"}, "Return@returnVersion": "2010v3.4"}