{"Return": {"ReturnHeader": {"PreparerFirm": {"PreparerFirmBusinessName": {"BusinessNameLine1": "OTIS ATWELL"}, "PreparerFirmUSAddress": {"AddressLine1": "324 GANNETT DRIVE", "City": "SOUTH PORTLAND", "State": "ME", "ZIPCode": "04106"}}, "Filer": {"Name": {"BusinessNameLine1": "FREEPORT HOUSING TRUST INC"}, "USAddress": {"AddressLine1": "P O BOX 625", "City": "FREEPORT", "State": "ME", "ZIPCode": "04032"}, "EIN": "010449761", "NameControl": "FREE", "Phone": "2078651652"}, "Officer": {"Name": "thomas whalen", "Title": "secretary/treasurer", "Phone": "2078651652", "DateSigned": "2011-01-10"}, "Preparer": {"Phone": "2077801100"}, "Timestamp": "2011-01-10T08:58:13-06:00", "TaxPeriodEndDate": "2010-09-30", "ReturnType": "990", "TaxPeriodBeginDate": "2009-10-01", "TaxYear": "2009", "BuildTS": "2016-02-24 21:20:13Z"}, "ReturnData": {"IRS990": {"AddressPrincipalOfficerUS": {"AddressLine1": "P O BOX 625", "City": "FREEPORT", "State": "ME", "ZIPCode": "04032"}, "Activity2": {"Expense": "125088", "Revenue": "136136", "Description": "OPERATION OF AN 18 UNIT LOW-INCOME HOUSING PROJECT KNOWN AS MAPLEWOOD TERRACE."}, "Activity3": {"Expense": "64530", "Revenue": "123164", "Description": "DEVELOPMENT AND MANAGEMENT OF VARIOUS LOW-INCOME HOUSING PROJECTS."}, "ActivityOther": {"Expense": "30068", "Revenue": "31566", "Description": "OPERATION OF A 4 UNIT LOW-INCOME PROJECT KNOWN AS BOW STREET"}, "TheBooksAreInCareOf": {"NameBusiness": {"BusinessNameLine1": "JAMES B HATCH"}, "AddressUS": {"AddressLine1": "PO BOX 625", "City": "freeport", "State": "ME", "ZIPCode": "04032"}, "TelephoneNumber": "2078651652"}, "Form990PartVIISectionA": [{"NamePerson": "chris RONEY", "Title": "PRESIDENT", "AverageHoursPerWeek": "3.00", "IndividualTrusteeOrDirector": "X", "Officer": "X", "ReportableCompFromOrganization": "0", "ReportableCompFromRelatedOrgs": "0", "OtherCompensation": "0"}, {"NamePerson": "john egan", "Title": "VICE PRESIDENT", "AverageHoursPerWeek": "2.00", "IndividualTrusteeOrDirector": "X", "Officer": "X", "ReportableCompFromOrganization": "0", "ReportableCompFromRelatedOrgs": "0", "OtherCompensation": "0"}, {"NamePerson": "thomas whelan", "Title": "treasurer", "AverageHoursPerWeek": "2.00", "IndividualTrusteeOrDirector": "X", "Officer": "X", "ReportableCompFromOrganization": "0", "ReportableCompFromRelatedOrgs": "0", "OtherCompensation": "0"}, {"NamePerson": "thomAS H KELLEY", "Title": "cLERK", "AverageHoursPerWeek": "2.00", "IndividualTrusteeOrDirector": "X", "Officer": "X", "ReportableCompFromOrganization": "0", "ReportableCompFromRelatedOrgs": "0", "OtherCompensation": "0"}, {"NamePerson": "joe burke", "Title": "dIRECTOR", "AverageHoursPerWeek": "1.00", "IndividualTrusteeOrDirector": "X", "ReportableCompFromOrganization": "0", "ReportableCompFromRelatedOrgs": "0", "OtherCompensation": "0"}, {"NamePerson": "maryellen carew", "Title": "DIRECTOR", "AverageHoursPerWeek": "1.00", "IndividualTrusteeOrDirector": "X", "ReportableCompFromOrganization": "0", "ReportableCompFromRelatedOrgs": "0", "OtherCompensation": "0"}, {"NamePerson": "dr jeff STENZEL", "Title": "DIRECTOR", "AverageHoursPerWeek": "1.00", "IndividualTrusteeOrDirector": "X", "ReportableCompFromOrganization": "0", "ReportableCompFromRelatedOrgs": "0", "OtherCompensation": "0"}, {"NamePerson": "amy cartmell", "Title": "secretary", "AverageHoursPerWeek": "1.00", "IndividualTrusteeOrDirector": "X", "Officer": "X", "ReportableCompFromOrganization": "0", "ReportableCompFromRelatedOrgs": "0", "OtherCompensation": "0"}, {"NamePerson": "dale whitmore", "Title": "dIRECTOR", "AverageHoursPerWeek": "1.00", "IndividualTrusteeOrDirector": "X", "ReportableCompFromOrganization": "0", "ReportableCompFromRelatedOrgs": "0", "OtherCompensation": "0"}, {"NamePerson": "betty langley", "Title": "dIRECTOR", "AverageHoursPerWeek": "1.00", "IndividualTrusteeOrDirector": "X", "ReportableCompFromOrganization": "0", "ReportableCompFromRelatedOrgs": "0", "OtherCompensation": "0"}, {"NamePerson": "edrol sandy", "Title": "dIRECTOR", "AverageHoursPerWeek": "1.00", "IndividualTrusteeOrDirector": "X", "ReportableCompFromOrganization": "0", "ReportableCompFromRelatedOrgs": "0", "OtherCompensation": "0"}], "ProgramServiceRevenue": [{"Description": "TENANT RENT", "BusinessCode": "531110", "TotalRevenueColumn": "355897", "RelatedOrExemptFunctionIncome": "355897"}, {"Description": "INCENTIVE MGMNT FEE", "BusinessCode": "531110", "TotalRevenueColumn": "50026", "RelatedOrExemptFunctionIncome": "50026"}, {"Description": "development fees", "BusinessCode": "531110", "TotalRevenueColumn": "18260", "RelatedOrExemptFunctionIncome": "18260"}, {"Description": "asset management fee", "BusinessCode": "531110", "TotalRevenueColumn": "12576", "RelatedOrExemptFunctionIncome": "12576"}, {"Description": "MANAGEMENT FEES", "BusinessCode": "531110", "TotalRevenueColumn": "5628", "RelatedOrExemptFunctionIncome": "5628"}], "TotalOthProgramServiceRevenue": {"TotalRevenueColumn": "3020", "RelatedOrExemptFunctionIncome": "3020"}, "InvestmentIncome": {"TotalRevenueColumn": "26342", "RelatedOrExemptFunctionIncome": "26342"}, "TotalRevenue": {"TotalRevenueColumn": "471749", "RelatedOrExemptFunctionIncome": "471749", "UnrelatedBusinessRevenue": "0", "ExclusionAmount": "0"}, "FeesForServicesManagement": {"Total": "42535", "ProgramServices": "42535"}, "FeesForServicesLegal": {"Total": "1239", "ProgramServices": "1239"}, "FeesForServicesAccounting": {"Total": "9800", "ProgramServices": "9800"}, "Travel": {"Total": "3294", "ProgramServices": "3294"}, "Interest": {"Total": "69447", "ProgramServices": "69447"}, "DepreciationDepletion": {"Total": "64205", "ProgramServices": "64205"}, "Insurance": {"Total": "9210", "ProgramServices": "9210"}, "OtherExpenses": [{"Description": "MAINTENANCE & REPAIRS", "Total": "49899", "ProgramServices": "49899"}, {"Description": "CONTRACTUAL SERVICES", "Total": "42666", "ProgramServices": "42666"}, {"Description": "consultant", "Total": "41005", "ProgramServices": "41005"}, {"Description": "UTILITIES", "Total": "28905", "ProgramServices": "28905"}, {"Description": "PROPERTY TAXES", "Total": "22340", "ProgramServices": "22340"}], "AllOtherExpenses": {"Total": "24061", "ProgramServices": "24061"}, "TotalFunctionalExpenses": {"Total": "408606", "ProgramServices": "408606", "ManagementAndGeneral": "0", "Fundraising": "0"}, "SavingsAndTempCashInvestments": {"BOY": "1117551", "EOY": "1158408"}, "AccountsReceivable": {"BOY": "4338", "EOY": "9011"}, "PrepaidExpensesDeferredCharges": {"BOY": "1220", "EOY": "73"}, "LandBuildingsEquipmentBasisNet": {"BOY": "1478362", "EOY": "1513381"}, "InvestmentsOtherSecurities": {"BOY": "3533"}, "InvestmentsProgramRelated": {"BOY": "595536", "EOY": "595536"}, "OtherAssetsTotal": {"BOY": "252749", "EOY": "249014"}, "TotalAssets": {"BOY": "3453289", "EOY": "3525423"}, "AccountsPayableAccruedExpenses": {"BOY": "15924", "EOY": "26832"}, "MortNotesPyblSecuredInvestProp": {"BOY": "1416661", "EOY": "1415741"}, "OtherLiabilities": {"BOY": "18925", "EOY": "17929"}, "TotalLiabilities": {"BOY": "1451510", "EOY": "1460502"}, "UnrestrictedNetAssets": {"BOY": "2001779", "EOY": "2064921"}, "TotalNetAssetsFundBalances": {"BOY": "2001779", "EOY": "2064921"}, "TotalLiabNetAssetsFundBalances": {"BOY": "3453289", "EOY": "3525423"}, "NameOfPrincipalOfficerPerson": "chris roney", "GrossReceipts": "471749", "GroupReturnForAffiliates": "0", "Organization501c@typeOf501cOrganization": "3", "Organization501c": "X", "WebSite": "N/A", "TypeOfOrganizationCorporation": "X", "YearFormation": "1991", "StateLegalDomicile": "ME", "ActivityOrMissionDescription": "PROVIDE LOW-INCOME HOUSING.", "NbrVotingMembersGoverningBody": "11", "NbrIndependentVotingMembers": "11", "TotalNbrEmployees": "0", "TotalNbrVolunteers": "0", "TotalGrossUBI": "0", "NetUnrelatedBusinessTxblIncome": "0", "ContributionsGrantsCurrentYear": "0", "ProgramServiceRevenuePriorYear": "437642", "ProgramServiceRevenueCY": "445407", "InvestmentIncomePriorYear": "30224", "InvestmentIncomeCurrentYear": "26342", "OtherRevenueCurrentYear": "0", "TotalRevenuePriorYear": "467866", "TotalRevenueCurrentYear": "471749", "GrantsAndSimilarAmntsCY": "0", "BenefitsPaidToMembersCY": "0", "SalariesEtcCurrentYear": "0", "TotalProfFundrsngExpCY": "0", "TotalFundrsngExpCurrentYear": "0", "OtherExpensePriorYear": "413056", "OtherExpensesCurrentYear": "408606", "TotalExpensesPriorYear": "413056", "TotalExpensesCurrentYear": "408606", "RevenuesLessExpensesPriorYear": "54810", "RevenuesLessExpensesCY": "63143", "TotalAssetsBOY": "3453289", "TotalAssetsEOY": "3525423", "TotalLiabilitiesBOY": "1451510", "TotalLiabilitiesEOY": "1460502", "NetAssetsOrFundBalancesBOY": "2001779", "NetAssetsOrFundBalancesEOY": "2064921", "MissionDescription": "PROVIDE LOW-INCOME HOUSING.", "SignificantNewProgramServices": "0", "SignificantChange": "0", "Expense": "188920", "Revenue": "180883", "Description": "OPERATION OF A 60 UNIT MOBILE HOME PARK KNOWN AS WARDTOWN PARK.", "TotalOfOtherProgramServiceExp": "30068", "TotalOfOtherProgramServiceRev": "31566", "TotalProgramServiceExpense": "408606", "DescribedIn501C3@referenceDocumentId": "RetDoc1039100001", "DescribedIn501C3": "1", "ScheduleBRequired": "0", "PoliticalActivities": "0", "LobbyingActivities": "0", "DonorAdvisedFunds@referenceDocumentId": "RetDoc1040000001", "DonorAdvisedFunds": "0", "ConservationEasements@referenceDocumentId": "RetDoc1040000001", "ConservationEasements": "0", "CollectionsOfArt@referenceDocumentId": "RetDoc1040000001", "CollectionsOfArt": "0", "CreditCounseling@referenceDocumentId": "RetDoc1040000001", "CreditCounseling": "0", "TermOrPermanentEndowments@referenceDocumentId": "RetDoc1040000001", "TermOrPermanentEndowments": "0", "BalanceSheetAmountsReported@referenceDocumentId": "RetDoc1040000001", "BalanceSheetAmountsReported": "1", "IndependentAuditFinancialStmt@referenceDocumentId": "RetDoc1040000001", "IndependentAuditFinancialStmt": "0", "ConsolidatedAuditFinancialStmt@referenceDocumentId": "RetDoc1040000001", "ConsolidatedAuditFinancialStmt": "0", "School": "0", "ForeignOffice": "0", "ForeignActivities": "0", "MoreThan5000KToOrganizations": "0", "MoreThan5000KToIndividuals": "0", "ProfessionalFundraising": "0", "FundraisingActivities": "0", "Gaming": "0", "Hospital": "0", "GrantsToOrganizations": "0", "GrantsToIndividuals": "0", "ScheduleJRequired": "0", "TaxExemptBonds": "0", "ExcessBenefitTransaction": "0", "PriorExcessBenefitTransaction": "0", "LoanToOfficerOrDQP": "0", "GrantToRelatedPerson": "0", "BsnssRltnshpWithOrganization": "0", "BsnssRltnshpThruFamilyMember": "0", "OfficerEntityWithBsnssRltnshp": "0", "DeductibleNonCashContributions": "0", "DeductibleContributionsOfArt": "0", "Terminated": "0", "PartialLiquidation": "0", "DisregardedEntity@referenceDocumentId": "RetDoc1043400001", "DisregardedEntity": "0", "RelatedEntity@referenceDocumentId": "RetDoc1043400001", "RelatedEntity": "1", "RelatedOrgControlledEntity@referenceDocumentId": "RetDoc1043400001", "RelatedOrgControlledEntity": "1", "TransfersToExemptNonChrtblOrg@referenceDocumentId": "RetDoc1043400001", "TransfersToExemptNonChrtblOrg": "0", "ActivitiesConductedPartnership@referenceDocumentId": "RetDoc1043400001", "ActivitiesConductedPartnership": "0", "ScheduleORequired": "1", "NumberFormsTransmittedWith1096": "0", "NumberW2GIncluded": "0", "NumberOfEmployees": "0", "UnrelatedBusinessIncome": "0", "ForeignFinancialAccount": "0", "ProhibitedTaxShelterTrans": "0", "TaxablePartyNotification": "0", "NonDeductibleContributions": "0", "NbrVotingGoverningBodyMembers": "11", "NumberIndependentVotingMembers": "11", "FamilyOrBusinessRelationship": "0", "DelegationOfManagementDuties": "0", "ChangesToOrganizingDocs": "0", "MaterialDiversionOrMisuse": "0", "MembersOrStockholders": "0", "ElectionOfBoardMembers": "1", "DecisionsSubjectToApproval": "0", "MinutesOfGoverningBody": "1", "MinutesOfCommittees": "1", "OfficerMailingAddress": "0", "LocalChapters": "0", "Form990ProvidedToGoverningBody": "1", "ConflictOfInterestPolicy": "1", "AnnualDisclosureCoveredPersons": "1", "RegularMonitoringEnforcement": "1", "WhistleblowerPolicy": "0", "DocumentRetentionPolicy": "0", "CompensationProcessCEO": "0", "CompensationProcessOther": "0", "InvestmentInJointVenture": "0", "UponRequest": "X", "NoListedPersonsCompensated": "X", "TotalReportableCompFromOrg": "0", "TotalReportableCompFrmRltdOrgs": "0", "TotalOtherCompensation": "0", "NumberIndividualsGT100K": "0", "FormersListed": "0", "TotalCompGT150K": "0", "CompensationFromOtherSources": "0", "NumberOfContractorsGT100K": "0", "TotalProgramServiceRevenue": "445407", "LandBuildingsEquipmentBasis": "2125342", "LandBldgEquipmentAccumDeprec": "611961", "FollowSFAS117": "X", "MethodOfAccountingAccrual": "X", "AccountantCompileOrReview": "1", "FSAudited": "0", "AuditCommittee": "1", "FinancialStatementConsolidated": "X", "FederalGrantAuditRequired": "0"}, "IRS990ScheduleA": {"GiftsGrantsContribReceived509": {"CurrentTaxYearMinus4Years": "186300", "Total": "186300"}, "GrossReceiptsFromAdmissions": {"CurrentTaxYearMinus4Years": "415457", "CurrentTaxYearMinus3Years": "382852", "CurrentTaxYearMinus2Years": "320955", "CurrentTaxYearMinus1Year": "433382", "CurrentTaxYear": "441355", "Total": "1994001"}, "Total509": {"CurrentTaxYearMinus4Years": "601757", "CurrentTaxYearMinus3Years": "382852", "CurrentTaxYearMinus2Years": "320955", "CurrentTaxYearMinus1Year": "433382", "CurrentTaxYear": "441355", "Total": "2180301"}, "AmtsRecdFromDisqualPersons": {"Total": "0"}, "AmtsFromSubstContributors": {"Total": "0"}, "SupportFromDQPsEtc": {"Total": "0"}, "GrossInvestmentIncome509": {"CurrentTaxYearMinus4Years": "40485", "CurrentTaxYearMinus3Years": "41098", "CurrentTaxYearMinus2Years": "36348", "CurrentTaxYearMinus1Year": "30224", "CurrentTaxYear": "26342", "Total": "174497"}, "InvestmentIncomeAndUBTI": {"CurrentTaxYearMinus4Years": "40485", "CurrentTaxYearMinus3Years": "41098", "CurrentTaxYearMinus2Years": "36348", "CurrentTaxYearMinus1Year": "30224", "CurrentTaxYear": "26342", "Total": "174497"}, "TotalSupportTotal": {"CurrentTaxYearMinus4Years": "642242", "CurrentTaxYearMinus3Years": "423950", "CurrentTaxYearMinus2Years": "357303", "CurrentTaxYearMinus1Year": "463606", "CurrentTaxYear": "467697", "Total": "2354798"}, "PubliclySupportedOrg509a2": "X", "PublicSupportTotal509": "2180301", "PublicSupportPercentage509": "0.92590", "PriorYearSupportPercentage": "0.93210", "InvestmentIncomePercentage": "0.07410", "PriorYrInvestIncomePercentage": "0.06790", "ThirtyThreePercntTestsCY509": "X"}, "IRS990ScheduleD": {"Land": {"OtherCostOrOtherBasis": "650594", "BookValue": "650594"}, "Buildings": {"OtherCostOrOtherBasis": "1474748", "Depreciation": "611961", "BookValue": "862787"}, "InvestmentsProgramRelated": [{"Description": "FHT HOLDINGS", "BookValue": "462219", "MethodOfValuation": "C"}, {"Description": "INVENTORY - CONDOMINIUMS", "BookValue": "133317", "MethodOfValuation": "C"}], "OtherAssets": [{"Description": "DEFERRED FINANCE FEES (NET OF AMORT)", "BookValue": "10533"}, {"Description": "TENANT SECURITY DEPOSITS", "BookValue": "15172"}, {"Description": "DUE FROM AFFILIATES", "BookValue": "17654"}, {"Description": "note receivable - related party", "BookValue": "205655"}], "OtherLiabilities": [{"Description": "TENANT SECURITY DEPOSITS", "Amount": "15117"}, {"Description": "PREPAID TENANT RENT", "Amount": "2812"}], "TotalOfBookValueLandBuildings": "1513381", "TotalOfBookValueProgramRelated": "595536", "TotalBookValueOtherAssets": "249014", "TotalOfAmounts": "17929"}, "IRS990ScheduleO": {"GeneralExplanation": [{"Identifier": "Form 990, Part VI, Section A, line 7a", "Explanation": "the board of directors are elected by its members."}, {"Identifier": "Form 990, Part VI, Section B, line 11", "Explanation": "the form 990 is reviewed by the treasurer prior to submission."}, {"Identifier": "Form 990, Part VI, Section B, line 12c", "Explanation": "board members regularly review any conflict of interest issues."}, {"Identifier": "Form 990, Part VI, Section C, line 19", "Explanation": "all organizing and operating documents are available to the public upon request."}]}, "IRS990ScheduleR": {"Form990ScheduleRPartII": {"NameOfDisregardedEntity": {"BusinessNameLine1": "oakleaf housing trust inc"}, "AddressUS": {"AddressLine1": "po box 625", "City": "freeport", "State": "ME", "ZIPCode": "04032"}, "EIN": "010492876", "PrimaryActivities": "ELDERLY housing", "LegalDomicileState": "ME", "ExemptCodeSection": "501(c)(3)", "PublicCharityStatus": "170(b)(1)(a)(vi)", "DirectControllingEntityNA": "N/A"}, "Form990ScheduleRPartIII": [{"NameOfRelatedOrg": {"BusinessNameLine1": "varney square associates lp"}, "AddressUS": {"AddressLine1": "po box 625", "City": "freeport", "State": "ME", "ZIPCode": "04032"}, "EIN": "201939305", "PrimaryActivity": "affordable housing", "LegalDomicileState": "ME", "DirectControllingEntityNA": "N/A", "PredominantIncomeType": "related", "ShareOfEOYAssets": "412", "DisproportionateAllocations": "0", "GeneralOrManagingPartner": "1"}, {"NameOfRelatedOrg": {"BusinessNameLine1": "freeport affordable housing lp"}, "AddressUS": {"AddressLine1": "po box 625", "City": "freeport", "State": "ME", "ZIPCode": "04032"}, "EIN": "010509768", "PrimaryActivity": "affordable housing", "LegalDomicileState": "ME", "DirectControllingEntityNA": "N/A", "PredominantIncomeType": "related", "ShareOfEOYAssets": "19423", "DisproportionateAllocations": "0", "GeneralOrManagingPartner": "1"}, {"NameOfRelatedOrg": {"BusinessNameLine1": "freeport elderly housing lp"}, "AddressUS": {"AddressLine1": "po box 625", "City": "freeport", "State": "ME", "ZIPCode": "04032"}, "EIN": "010539012", "PrimaryActivity": "affordable housing", "LegalDomicileState": "ME", "DirectControllingEntityNA": "N/A", "PredominantIncomeType": "related", "ShareOfEOYAssets": "90", "DisproportionateAllocations": "0", "GeneralOrManagingPartner": "1"}], "Form990ScheduleRPartIV": {"NameOfRelatedOrg": {"BusinessNameLine1": "fht holdings inc"}, "AddressUS": {"AddressLine1": "po box 625", "City": "freeport", "State": "ME", "ZIPCode": "04032"}, "EIN": "010509766", "PrimaryActivity": "affordable housing", "LegalDomicileState": "ME", "TypeOfEntity": "C", "ShareOfTotalIncome": "2", "ShareOfEOYAssets": "440667", "PercentageOwnership": "1.00000"}, "TransactionsRelatedOrgsTable": [{"NameOfOtherOrganization": {"BusinessNameLine1": "VARNEY SQUARE ASSOCIATES LP"}, "TransactionType": "K", "AmountInvolved": "18260"}, {"NameOfOtherOrganization": {"BusinessNameLine1": "OAKLEAF HOUSING TRUST INC"}, "TransactionType": "K", "AmountInvolved": "5628"}, {"NameOfOtherOrganization": {"BusinessNameLine1": "Freeport affordable housing lp"}, "TransactionType": "K", "AmountInvolved": "12298"}, {"NameOfOtherOrganization": {"BusinessNameLine1": "freeport elderly housing lp"}, "TransactionType": "K", "AmountInvolved": "50304"}], "ReceiptOfIntAnnRentsRoyalties": "0", "GiftGrantOrCapContrToOtherOrg": "0", "GiftGrantOrCapContrFrOtherOrg": "0", "LoansOrGuaranteesToOtherOrg": "0", "LoansOrGuaranteesFromOtherOrg": "0", "SaleOfAssetsToOtherOrg": "0", "PurchaseOfAssetsFromOtherOrg": "0", "ExchangeOfAssets": "0", "RentalOfFacilitiesToOtherOrgs": "0", "RentalOfFacilitiesFrOtherOrgs": "0", "PerformOfServicesForOtherOrgs": "1", "PerformOfServicesByOtherOrgs": "0", "SharingOfFacilities": "0", "SharingOfPaidEmployees": "0", "ReimbursementPaidToOtherOrg": "0", "ReimbursementPaidByOtherOrg": "0", "OtherTransferToOtherOrg": "0", "OtherTransferFromOtherOrg": "0"}, "IRS990@documentId": "RetDoc1038000001", "IRS990@referenceDocumentId": "RetDoc1044400001", "IRS990ScheduleA@documentId": "RetDoc1039100001", "IRS990ScheduleD@documentId": "RetDoc1040000001", "IRS990ScheduleO@documentId": "RetDoc1044400001", "IRS990ScheduleR@documentId": "RetDoc1043400001"}, "ReturnHeader@binaryAttachmentCount": "0", "ReturnData@documentCount": "5"}, "Return@returnVersion": "2009v1.4"}